aimusic_mcp-1.0.6.dist-info/licenses/LICENSE
musicmcp_ai_mcp/__init__.py
musicmcp_ai_mcp/__main__.py
musicmcp_ai_mcp/api.py
aimusic_mcp-1.0.6.dist-info/METADATA
aimusic_mcp-1.0.6.dist-info/WHEEL
aimusic_mcp-1.0.6.dist-info/entry_points.txt
aimusic_mcp-1.0.6.dist-info/top_level.txt
aimusic_mcp-1.0.6.dist-info/RECORD
