Metadata-Version: 2.4
Name: aimusic-mcp
Version: 1.0.6
Summary: The MCP server of MusicMCP.AI - AI Music Generation Platform
Author-email: "MusicMCP.AI Team" <support@musicmcp.ai>
Project-URL: Homepage, https://www.musicmcp.ai
Keywords: aimusic,musicmcp,mcp,music,song,ai,generate,model-context-protocol
Classifier: Development Status :: 4 - Beta
Classifier: Intended Audience :: Developers
Classifier: License :: OSI Approved :: MIT License
Classifier: Programming Language :: Python :: 3
Classifier: Programming Language :: Python :: 3.10
Classifier: Programming Language :: Python :: 3.11
Classifier: Programming Language :: Python :: 3.12
Classifier: Topic :: Multimedia :: Sound/Audio
Classifier: Topic :: Software Development :: Libraries :: Python Modules
Requires-Python: >=3.10
License-File: LICENSE
Requires-Dist: mcp[cli]>=1.6.0
Requires-Dist: httpx>=0.24.0
Dynamic: license-file
